friendly/__init__.py
friendly/__main__.py
friendly/console.py
friendly/idle_writer.py
friendly/ipython.py
friendly/jupyter.py
friendly/my_gettext.py
friendly/py.typed
friendly/rich_console_helpers.py
friendly/rich_formatters.py
friendly/settings.py
friendly/idle/__init__.py
friendly/idle/get_syntax.py
friendly/idle/main.py
friendly/idle/patch_source_cache.py
friendly/ipython_common/__init__.py
friendly/ipython_common/excepthook.py
friendly/ipython_common/settings.py
friendly/locales/friendly.pot
friendly/locales/es/LC_MESSAGES/friendly_es.mo
friendly/locales/es/LC_MESSAGES/friendly_es.po
friendly/locales/fr/LC_MESSAGES/friendly_fr.mo
friendly/locales/fr/LC_MESSAGES/friendly_fr.po
friendly/locales/ru/LC_MESSAGES/friendly_ru.mo
friendly/locales/ru/LC_MESSAGES/friendly_ru.po
friendly/mu/__init__.py
friendly/mu/repl.py
friendly/mu/runner.py
friendly/theme/__init__.py
friendly/theme/colours.py
friendly/theme/friendly_pygments.py
friendly/theme/friendly_rich.py
friendly/theme/patch_tb_lexer.py
friendly-0.7.21.dist-info/LICENSE
friendly-0.7.21.dist-info/METADATA
friendly-0.7.21.dist-info/WHEEL
friendly-0.7.21.dist-info/entry_points.txt
friendly-0.7.21.dist-info/top_level.txt
friendly-0.7.21.dist-info/RECORD
