Metadata-Version: 2.1
Name: friendly
Version: 0.7.21
Summary: Friendlier tracebacks in any language.
Home-page: https://github.com/friendly-traceback/friendly
Author: Andre Roberge
Author-email: Andre.Roberge@gmail.com
Classifier: Development Status :: 4 - Beta
Classifier: Environment :: Console
Classifier: License :: OSI Approved :: MIT License
Classifier: Natural Language :: English
Classifier: Natural Language :: French
Classifier: Programming Language :: Python :: 3
Classifier: Programming Language :: Python :: 3.6
Classifier: Programming Language :: Python :: 3.7
Classifier: Programming Language :: Python :: 3.8
Classifier: Programming Language :: Python :: 3.9
Classifier: Programming Language :: Python :: 3.10
Classifier: Intended Audience :: Education
Classifier: Topic :: Education
Classifier: Topic :: Software Development :: Interpreters
Requires-Python: >=3.6.1
License-File: LICENSE
